LICENSE
MANIFEST.in
README.rst
setup.py
zabbix_api.py
zabbix_api_erigones.egg-info/PKG-INFO
zabbix_api_erigones.egg-info/SOURCES.txt
zabbix_api_erigones.egg-info/dependency_links.txt
zabbix_api_erigones.egg-info/top_level.txt