Metadata-Version: 1.1
Name: zabbix-api-erigones
Version: 1.2.4
Summary: Zabbix API Python Library
Home-page: https://github.com/erigones/zabbix-api/
Author: Erigones
Author-email: erigones@erigones.com
License: LGPL
Platform: any
Classifier: Environment :: Console
Classifier: Environment :: Plugins
Classifier: Intended Audience :: System Administrators
Classifier: Intended Audience :: Developers
Classifier: License :: OSI Approved :: GNU Library or Lesser General Public License (LGPL)
Classifier: Programming Language :: Python
Classifier: Programming Language :: Python :: 2
Classifier: Programming Language :: Python :: 3
Classifier: Development Status :: 5 - Production/Stable
Classifier: Topic :: Software Development :: Libraries
Classifier: Topic :: System :: Monitoring
Classifier: Topic :: Utilities
